<?xml version="1.0" encoding="utf-8" ?>
<elements>
	<info>
		<update version="0.0.1">
			<file name="source.xml" url="https://raw.githubusercontent.com/AuroraLegacy/elements/master/supplements/astarions-book-of-hungers/source.xml" />
		</update>
	</info>
	<element name="Astarion’s Book of Hungers" type="Source" source="Core" id="ID_WOTC_SOURCE_ASTARIONS_BOOK_OF_HUNGERS">
		<description>
			<![CDATA[<p>Fight, flirt, or feast your way through the shadows of Baldur's Gate in this digital expansion, complete with new character options, devilish monsters, and tavern-set escapades dripping with blood and intrigue.</p>
			<p class="indent">Join Astarion in 2 play-ready digital adventures and explore the seductive horrors of vampiric power with new backgrounds, feats, and more.</p>]]>
		</description>
		<setters>
			<set name="abbreviation">ABH</set>
			<set name="url">https://marketplace.dndbeyond.com/adventures/DBRWE7DB3</set>
			<set name="image">https://raw.githubusercontent.com/AuroraLegacy/elements/master/supplements/astarions-book-of-hungers/ABH.png</set>
			<set name="author" abbreviation="WOTC" url="http://dnd.wizards.com">Wizards of the Coast</set>
			<set name="official">true</set>
			<set name="core">false</set>
			<set name="supplement">true</set>
			<set name="release">20251111</set>
		</setters>
	</element>
</elements>
